{
    "key": "group_65d616d0e2170",
    "title": "Global Typography",
    "fields": [
        {
            "key": "field_65d616d0e7342",
            "label": "Primary Import Font Family",
            "name": "primary_import_font_family",
            "aria-label": "",
            "type": "textarea",
            "instructions": "Please add the @import url. For example: https:\/\/fonts.googleapis.com\/css2?family=Open+Sans&display=swap",
            "required": 0,
            "conditional_logic": 0,
            "wrapper": {
                "width": "",
                "class": "",
                "id": ""
            },
            "default_value": "",
            "maxlength": "",
            "rows": "",
            "placeholder": "",
            "new_lines": ""
        },
        {
            "key": "field_65d8c34ae7d6d",
            "label": "Primary Font Family",
            "name": "primary_font_family",
            "aria-label": "",
            "type": "text",
            "instructions": "Please copy the font family name",
            "required": 0,
            "conditional_logic": 0,
            "wrapper": {
                "width": "",
                "class": "",
                "id": ""
            },
            "default_value": "",
            "maxlength": "",
            "placeholder": "",
            "prepend": "",
            "append": ""
        },
        {
            "key": "field_65dcba6f90c30",
            "label": "Secondary Font Family",
            "name": "secondary_font_family",
            "aria-label": "",
            "type": "text",
            "instructions": "Please copy the font family name",
            "required": 0,
            "conditional_logic": 0,
            "wrapper": {
                "width": "",
                "class": "",
                "id": ""
            },
            "default_value": "",
            "maxlength": "",
            "placeholder": "",
            "prepend": "",
            "append": ""
        },
        {
            "key": "field_65d616d0e6bef",
            "label": "H1",
            "name": "font_h1",
            "aria-label": "",
            "type": "group",
            "instructions": "",
            "required": 0,
            "conditional_logic": 0,
            "wrapper": {
                "width": "",
                "class": "",
                "id": ""
            },
            "layout": "block",
            "sub_fields": [
                {
                    "key": "field_65d616d0eb383",
                    "label": "Font Weight",
                    "name": "font_weight",
                    "aria-label": "",
                    "type": "select",
                    "instructions": "",
                    "required": 0,
                    "conditional_logic": 0,
                    "wrapper": {
                        "width": "",
                        "class": "",
                        "id": ""
                    },
                    "choices": {
                        "100": "Thin (100)",
                        "200": "Extra Light (200)",
                        "300": "Light (300)",
                        "400": "Regular (400)",
                        "500": "Medium (500)",
                        "600": "Semi-Bold (600)",
                        "700": "Bold (700)",
                        "800": "Extra Bold (800)",
                        "900": "Black (900)"
                    },
                    "default_value": 500,
                    "return_format": "value",
                    "multiple": 0,
                    "allow_null": 0,
                    "ui": 0,
                    "ajax": 0,
                    "placeholder": ""
                },
                {
                    "key": "field_65d616d0eb389",
                    "label": "Family",
                    "name": "font_family",
                    "aria-label": "",
                    "type": "select",
                    "instructions": "",
                    "required": 0,
                    "conditional_logic": [
                        [
                            {
                                "field": "field_65d8c34ae7d6d",
                                "operator": "!=empty"
                            }
                        ],
                        [
                            {
                                "field": "field_65dcba6f90c30",
                                "operator": "!=empty"
                            }
                        ]
                    ],
                    "wrapper": {
                        "width": "",
                        "class": "",
                        "id": ""
                    },
                    "choices": {
                        "primary_font": "Primary",
                        "secondary_font": "Secondary"
                    },
                    "default_value": false,
                    "return_format": "value",
                    "multiple": 0,
                    "allow_null": 0,
                    "ui": 0,
                    "ajax": 0,
                    "placeholder": ""
                }
            ]
        },
        {
            "key": "field_65d616d0e6bf8",
            "label": "H2",
            "name": "font_h2",
            "aria-label": "",
            "type": "group",
            "instructions": "",
            "required": 0,
            "conditional_logic": 0,
            "wrapper": {
                "width": "",
                "class": "",
                "id": ""
            },
            "layout": "block",
            "sub_fields": [
                {
                    "key": "field_65d616d0ed687",
                    "label": "Font Weight",
                    "name": "font_weight",
                    "aria-label": "",
                    "type": "select",
                    "instructions": "",
                    "required": 0,
                    "conditional_logic": 0,
                    "wrapper": {
                        "width": "",
                        "class": "",
                        "id": ""
                    },
                    "choices": {
                        "100": "Thin (100)",
                        "200": "Extra Light (200)",
                        "300": "Light (300)",
                        "400": "Regular (400)",
                        "500": "Medium (500)",
                        "600": "Semi-Bold (600)",
                        "700": "Bold (700)",
                        "800": "Extra Bold (800)",
                        "900": "Black (900)"
                    },
                    "default_value": 500,
                    "return_format": "value",
                    "multiple": 0,
                    "allow_null": 0,
                    "ui": 0,
                    "ajax": 0,
                    "placeholder": ""
                },
                {
                    "key": "field_65d616d0ed68f",
                    "label": "Family",
                    "name": "font_family",
                    "aria-label": "",
                    "type": "select",
                    "instructions": "",
                    "required": 0,
                    "conditional_logic": 0,
                    "wrapper": {
                        "width": "",
                        "class": "",
                        "id": ""
                    },
                    "choices": {
                        "primary_font": "Primary",
                        "secondary_font": "Secondary"
                    },
                    "default_value": false,
                    "return_format": "value",
                    "multiple": 0,
                    "allow_null": 0,
                    "ui": 0,
                    "ajax": 0,
                    "placeholder": ""
                }
            ]
        },
        {
            "key": "field_65d616d0e6bff",
            "label": "H3",
            "name": "font_h3",
            "aria-label": "",
            "type": "group",
            "instructions": "",
            "required": 0,
            "conditional_logic": 0,
            "wrapper": {
                "width": "",
                "class": "",
                "id": ""
            },
            "layout": "block",
            "sub_fields": [
                {
                    "key": "field_65d616d0ef8e1",
                    "label": "Font Weight",
                    "name": "font_weight",
                    "aria-label": "",
                    "type": "select",
                    "instructions": "",
                    "required": 0,
                    "conditional_logic": 0,
                    "wrapper": {
                        "width": "",
                        "class": "",
                        "id": ""
                    },
                    "choices": {
                        "100": "Thin (100)",
                        "200": "Extra Light (200)",
                        "300": "Light (300)",
                        "400": "Regular (400)",
                        "500": "Medium (500)",
                        "600": "Semi-Bold (600)",
                        "700": "Bold (700)",
                        "800": "Extra Bold (800)",
                        "900": "Black (900)"
                    },
                    "default_value": 500,
                    "return_format": "value",
                    "multiple": 0,
                    "allow_null": 0,
                    "ui": 0,
                    "ajax": 0,
                    "placeholder": ""
                },
                {
                    "key": "field_65d616d0ef8e5",
                    "label": "Family",
                    "name": "font_family",
                    "aria-label": "",
                    "type": "select",
                    "instructions": "",
                    "required": 0,
                    "conditional_logic": 0,
                    "wrapper": {
                        "width": "",
                        "class": "",
                        "id": ""
                    },
                    "choices": {
                        "primary_font": "Primary",
                        "secondary_font": "Secondary"
                    },
                    "default_value": false,
                    "return_format": "value",
                    "multiple": 0,
                    "allow_null": 0,
                    "ui": 0,
                    "ajax": 0,
                    "placeholder": ""
                }
            ]
        },
        {
            "key": "field_65d61d45b33a2",
            "label": "H4",
            "name": "font_h4",
            "aria-label": "",
            "type": "group",
            "instructions": "",
            "required": 0,
            "conditional_logic": 0,
            "wrapper": {
                "width": "",
                "class": "",
                "id": ""
            },
            "layout": "block",
            "sub_fields": [
                {
                    "key": "field_65d61d45b33a3",
                    "label": "Font Weight",
                    "name": "font_weight",
                    "aria-label": "",
                    "type": "select",
                    "instructions": "",
                    "required": 0,
                    "conditional_logic": 0,
                    "wrapper": {
                        "width": "",
                        "class": "",
                        "id": ""
                    },
                    "choices": {
                        "100": "Thin (100)",
                        "200": "Extra Light (200)",
                        "300": "Light (300)",
                        "400": "Regular (400)",
                        "500": "Medium (500)",
                        "600": "Semi-Bold (600)",
                        "700": "Bold (700)",
                        "800": "Extra Bold (800)",
                        "900": "Black (900)"
                    },
                    "default_value": 500,
                    "return_format": "value",
                    "multiple": 0,
                    "allow_null": 0,
                    "ui": 0,
                    "ajax": 0,
                    "placeholder": ""
                },
                {
                    "key": "field_65d61d45b33a4",
                    "label": "Family",
                    "name": "font_family",
                    "aria-label": "",
                    "type": "select",
                    "instructions": "",
                    "required": 0,
                    "conditional_logic": 0,
                    "wrapper": {
                        "width": "",
                        "class": "",
                        "id": ""
                    },
                    "choices": {
                        "primary_font": "Primary",
                        "secondary_font": "Secondary"
                    },
                    "default_value": false,
                    "return_format": "value",
                    "multiple": 0,
                    "allow_null": 0,
                    "ui": 0,
                    "ajax": 0,
                    "placeholder": ""
                }
            ]
        }
    ],
    "location": [
        [
            {
                "param": "customizer",
                "operator": "==",
                "value": "globaltypography"
            }
        ]
    ],
    "menu_order": 0,
    "position": "normal",
    "style": "default",
    "label_placement": "top",
    "instruction_placement": "label",
    "hide_on_screen": "",
    "active": true,
    "description": "",
    "show_in_rest": 0,
    "modified": 1709743476
}
